{
    "folder": {
        "create": {
            "modal": {
                "title": "",
                "input": {
                    "label": {
                        "name": ""
                    }
                },
                "button": {
                    "confirm": ""
                }
            }
        }
    },
    "modal": {
        "button": {
            "cancel": "",
            "confirm": ""
        }
    },
    "node": {
        "rename": {
            "modal": {
                "button": {
                    "confirm": ""
                },
                "input": {
                    "label": {
                        "name": ""
                    }
                },
                "title": ""
            }
        }
    },
    "primaryBar": {
        "driveHome": ""
    },
    "secondaryBar": {
        "driveHome": "",
        "filters": "",
        "filtersList": {
            "flagged": ""
        },
        "team": ""
    },
    "snackbar": {
        "markForDeletion": {
            "error": "",
            "success": ""
        }
    },
    "create": {
        "options": {
            "new": {
                "folder": ""
            }
        }
    },
    "empty": {
        "folder": {
            "hint": "",
            "state": ""
        }
    },
    "filter": {
        "snackbar": {
            "unflag": {
                "error": "",
                "success": ""
            }
        }
    }
}
